rst/linker.py
rst.linker-2.5.0.dist-info/LICENSE
rst.linker-2.5.0.dist-info/METADATA
rst.linker-2.5.0.dist-info/WHEEL
rst.linker-2.5.0.dist-info/top_level.txt
rst.linker-2.5.0.dist-info/RECORD
